{
    "fluentMethods": true,
    "relationships": [
        {
            "relationshipName": "persona",
            "otherEntityName": "persona",
            "relationshipType": "one-to-one",
            "relationshipValidateRules": [
                "required"
            ],
            "otherEntityField": "nombre",
            "ownerSide": true,
            "otherEntityRelationshipName": "proveedor"
        }
    ],
    "fields": [
        {
            "fieldName": "nombreProveedor",
            "fieldType": "String",
            "fieldValidateRules": [
                "required"
            ]
        }
    ],
    "changelogDate": "20171214021518",
    "dto": "no",
    "searchEngine": false,
    "service": "serviceClass",
    "entityTableName": "proveedor",
    "databaseType": "sql",
    "jpaMetamodelFiltering": false,
    "pagination": "pagination"
}
